api_server.py
config.py
dynamic_cot_controller.py
llm_client.py
veltraxor.py
veltraxor-0.1.0.dist-info/METADATA
veltraxor-0.1.0.dist-info/WHEEL
veltraxor-0.1.0.dist-info/entry_points.txt
veltraxor-0.1.0.dist-info/top_level.txt
veltraxor-0.1.0.dist-info/RECORD
