Metadata-Version: 2.4
Name: veltraxor
Version: 0.1.0
Summary: CLI / API chatbot with Dynamic CoT controller
Author: YOUR_NAME
Requires-Python: >=3.9
Requires-Dist: python-dotenv>=1.0.0
Requires-Dist: requests>=2.25.1
Requires-Dist: httpx>=0.27.0
Requires-Dist: fastapi>=0.115.0
Requires-Dist: uvicorn>=0.34.0
Requires-Dist: pydantic-settings>=2.1.0
Provides-Extra: dev
Requires-Dist: pytest>=7.0; extra == "dev"
Requires-Dist: wheel>=0.40; extra == "dev"
Requires-Dist: build>=1.0; extra == "dev"
Dynamic: author
Dynamic: provides-extra
Dynamic: requires-dist
Dynamic: requires-python
Dynamic: summary
